cli_ih/__init__.py
cli_ih/asyncClient.py
cli_ih/client.py
cli_ih/exceptions.py
venv/Lib/site-packages/__editable___cli_ih_0_6_3_1_finder.py
venv/Lib/site-packages/pip/__init__.py
venv/Lib/site-packages/pip/__main__.py
venv/Lib/site-packages/pip/__pip-runner__.py
venv/Lib/site-packages/pip/py.typed
venv/Lib/site-packages/pip/_internal/__init__.py
venv/Lib/site-packages/pip/_internal/build_env.py
venv/Lib/site-packages/pip/_internal/cache.py
venv/Lib/site-packages/pip/_internal/configuration.py
venv/Lib/site-packages/pip/_internal/exceptions.py
venv/Lib/site-packages/pip/_internal/main.py
venv/Lib/site-packages/pip/_internal/pyproject.py
venv/Lib/site-packages/pip/_internal/self_outdated_check.py
venv/Lib/site-packages/pip/_internal/wheel_builder.py
venv/Lib/site-packages/pip/_internal/cli/__init__.py
venv/Lib/site-packages/pip/_internal/cli/autocompletion.py
venv/Lib/site-packages/pip/_internal/cli/base_command.py
venv/Lib/site-packages/pip/_internal/cli/cmdoptions.py
venv/Lib/site-packages/pip/_internal/cli/command_context.py
venv/Lib/site-packages/pip/_internal/cli/index_command.py
venv/Lib/site-packages/pip/_internal/cli/main.py
venv/Lib/site-packages/pip/_internal/cli/main_parser.py
venv/Lib/site-packages/pip/_internal/cli/parser.py
venv/Lib/site-packages/pip/_internal/cli/progress_bars.py
venv/Lib/site-packages/pip/_internal/cli/req_command.py
venv/Lib/site-packages/pip/_internal/cli/spinners.py
venv/Lib/site-packages/pip/_internal/cli/status_codes.py
venv/Lib/site-packages/pip/_internal/commands/__init__.py
venv/Lib/site-packages/pip/_internal/commands/cache.py
venv/Lib/site-packages/pip/_internal/commands/check.py
venv/Lib/site-packages/pip/_internal/commands/completion.py
venv/Lib/site-packages/pip/_internal/commands/configuration.py
venv/Lib/site-packages/pip/_internal/commands/debug.py
venv/Lib/site-packages/pip/_internal/commands/download.py
venv/Lib/site-packages/pip/_internal/commands/freeze.py
venv/Lib/site-packages/pip/_internal/commands/hash.py
cli_ih-0.6.3.1.dist-info/METADATA
cli_ih-0.6.3.1.dist-info/WHEEL
cli_ih-0.6.3.1.dist-info/top_level.txt
cli_ih-0.6.3.1.dist-info/RECORD
