Metadata-Version: 2.4
Name: cli_ih
Version: 0.6.3.1
Summary: A background command handler for python's command-line interface.
Author-email: Hotment <michatchuplay@gmail.com>
Requires-Python: >=3.8
